{
    "face_highlight_map": {
        "red": [
            "12",
            "22",
            "23",
            "24",
            "33",
            "42",
            "43",
            "44",
            "45",
            "46",
            "47",
            "48",
            "49",
            "11",
            "35",
            "36",
            "37",
            "38",
            "39",
            "40",
            "41",
            "50",
            "13",
            "25",
            "26",
            "27",
            "28",
            "29",
            "30",
            "31",
            "32",
            "42",
            "43",
            "44",
            "45",
            "46",
            "47",
            "48",
            "49",
            "42",
            "43",
            "44",
            "45",
            "46",
            "47",
            "48",
            "49",
            "25",
            "26",
            "27",
            "28",
            "29",
            "30",
            "31",
            "32",
            "25",
            "26",
            "27",
            "28",
            "29",
            "30",
            "31",
            "32"
        ],
        "yellow": [
            "1",
            "60",
            "2",
            "59",
            "3",
            "58",
            "4",
            "57",
            "5",
            "56",
            "6",
            "55",
            "7",
            "54",
            "8",
            "53",
            "9",
            "52"
        ]
    },
    "file": "",
    "report_version": "2.0",
    "summary": {
        "red_count": 6,
        "total_violations": 15,
        "yellow_count": 9
    },
    "timestamp": "2026-02-10T15:18:07",
    "violations": [
        {
            "affected_face_ids": [
                "1",
                "60"
            ],
            "location": {
                "x": 0.0,
                "y": 0.0,
                "z": 0.0
            },
            "measured_value": 4.2,
            "message": "孔径Ø4.20mm为非标准尺寸，最近的标准尺寸为Ø4.00mm（差值0.20mm），需要定制刀具或钻扩铰组合工艺，成本增加2-5倍",
            "rule_id": "DRILL_NON_STANDARD_DIAMETER",
            "rule_name": "非标准孔径",
            "severity": "yellow",
            "suggestions": [
                "修改为标准尺寸Ø4.0mm",
                "use_drill_reamer_combination",
                "use_milling_if_tolerance_loose"
            ],
            "threshold": 4.0
        },
        {
            "affected_face_ids": [
                "2",
                "59"
            ],
            "location": {
                "x": 0.0,
                "y": 0.0,
                "z": 0.0
            },
            "measured_value": 4.2,
            "message": "孔径Ø4.20mm为非标准尺寸，最近的标准尺寸为Ø4.00mm（差值0.20mm），需要定制刀具或钻扩铰组合工艺，成本增加2-5倍",
            "rule_id": "DRILL_NON_STANDARD_DIAMETER",
            "rule_name": "非标准孔径",
            "severity": "yellow",
            "suggestions": [
                "修改为标准尺寸Ø4.0mm",
                "use_drill_reamer_combination",
                "use_milling_if_tolerance_loose"
            ],
            "threshold": 4.0
        },
        {
            "affected_face_ids": [
                "3",
                "58"
            ],
            "location": {
                "x": 0.0,
                "y": 0.0,
                "z": 0.0
            },
            "measured_value": 4.2,
            "message": "孔径Ø4.20mm为非标准尺寸，最近的标准尺寸为Ø4.00mm（差值0.20mm），需要定制刀具或钻扩铰组合工艺，成本增加2-5倍",
            "rule_id": "DRILL_NON_STANDARD_DIAMETER",
            "rule_name": "非标准孔径",
            "severity": "yellow",
            "suggestions": [
                "修改为标准尺寸Ø4.0mm",
                "use_drill_reamer_combination",
                "use_milling_if_tolerance_loose"
            ],
            "threshold": 4.0
        },
        {
            "affected_face_ids": [
                "4",
                "57"
            ],
            "location": {
                "x": 0.0,
                "y": 0.0,
                "z": 0.0
            },
            "measured_value": 4.2,
            "message": "孔径Ø4.20mm为非标准尺寸，最近的标准尺寸为Ø4.00mm（差值0.20mm），需要定制刀具或钻扩铰组合工艺，成本增加2-5倍",
            "rule_id": "DRILL_NON_STANDARD_DIAMETER",
            "rule_name": "非标准孔径",
            "severity": "yellow",
            "suggestions": [
                "修改为标准尺寸Ø4.0mm",
                "use_drill_reamer_combination",
                "use_milling_if_tolerance_loose"
            ],
            "threshold": 4.0
        },
        {
            "affected_face_ids": [
                "5",
                "56"
            ],
            "location": {
                "x": 0.0,
                "y": 0.0,
                "z": 0.0
            },
            "measured_value": 4.2,
            "message": "孔径Ø4.20mm为非标准尺寸，最近的标准尺寸为Ø4.00mm（差值0.20mm），需要定制刀具或钻扩铰组合工艺，成本增加2-5倍",
            "rule_id": "DRILL_NON_STANDARD_DIAMETER",
            "rule_name": "非标准孔径",
            "severity": "yellow",
            "suggestions": [
                "修改为标准尺寸Ø4.0mm",
                "use_drill_reamer_combination",
                "use_milling_if_tolerance_loose"
            ],
            "threshold": 4.0
        },
        {
            "affected_face_ids": [
                "6",
                "55"
            ],
            "location": {
                "x": 0.0,
                "y": 0.0,
                "z": 0.0
            },
            "measured_value": 4.2,
            "message": "孔径Ø4.20mm为非标准尺寸，最近的标准尺寸为Ø4.00mm（差值0.20mm），需要定制刀具或钻扩铰组合工艺，成本增加2-5倍",
            "rule_id": "DRILL_NON_STANDARD_DIAMETER",
            "rule_name": "非标准孔径",
            "severity": "yellow",
            "suggestions": [
                "修改为标准尺寸Ø4.0mm",
                "use_drill_reamer_combination",
                "use_milling_if_tolerance_loose"
            ],
            "threshold": 4.0
        },
        {
            "affected_face_ids": [
                "7",
                "54"
            ],
            "location": {
                "x": 0.0,
                "y": 0.0,
                "z": 0.0
            },
            "measured_value": 4.2,
            "message": "孔径Ø4.20mm为非标准尺寸，最近的标准尺寸为Ø4.00mm（差值0.20mm），需要定制刀具或钻扩铰组合工艺，成本增加2-5倍",
            "rule_id": "DRILL_NON_STANDARD_DIAMETER",
            "rule_name": "非标准孔径",
            "severity": "yellow",
            "suggestions": [
                "修改为标准尺寸Ø4.0mm",
                "use_drill_reamer_combination",
                "use_milling_if_tolerance_loose"
            ],
            "threshold": 4.0
        },
        {
            "affected_face_ids": [
                "8",
                "53"
            ],
            "location": {
                "x": 0.0,
                "y": 0.0,
                "z": 0.0
            },
            "measured_value": 4.2,
            "message": "孔径Ø4.20mm为非标准尺寸，最近的标准尺寸为Ø4.00mm（差值0.20mm），需要定制刀具或钻扩铰组合工艺，成本增加2-5倍",
            "rule_id": "DRILL_NON_STANDARD_DIAMETER",
            "rule_name": "非标准孔径",
            "severity": "yellow",
            "suggestions": [
                "修改为标准尺寸Ø4.0mm",
                "use_drill_reamer_combination",
                "use_milling_if_tolerance_loose"
            ],
            "threshold": 4.0
        },
        {
            "affected_face_ids": [
                "9",
                "52"
            ],
            "location": {
                "x": 0.0,
                "y": 0.0,
                "z": 0.0
            },
            "measured_value": 4.2,
            "message": "孔径Ø4.20mm为非标准尺寸，最近的标准尺寸为Ø4.00mm（差值0.20mm），需要定制刀具或钻扩铰组合工艺，成本增加2-5倍",
            "rule_id": "DRILL_NON_STANDARD_DIAMETER",
            "rule_name": "非标准孔径",
            "severity": "yellow",
            "suggestions": [
                "修改为标准尺寸Ø4.0mm",
                "use_drill_reamer_combination",
                "use_milling_if_tolerance_loose"
            ],
            "threshold": 4.0
        },
        {
            "affected_face_ids": [
                "12",
                "22",
                "23",
                "24",
                "33",
                "42",
                "43",
                "44",
                "45",
                "46",
                "47",
                "48",
                "49",
                "11",
                "35",
                "36",
                "37",
                "38",
                "39",
                "40",
                "41",
                "50"
            ],
            "location": {
                "x": 0.0,
                "y": 0.0,
                "z": 0.0
            },
            "measured_value": 93.52941176470588,
            "message": "型腔深度159.00mm，最小宽度1.70mm，深宽比93.53大于硬阈值6.00",
            "rule_id": "MILL_DEEP_POCKET",
            "rule_name": "深腔",
            "severity": "red",
            "suggestions": [
                "reduce_depth",
                "increase_opening_width",
                "use_stepdown_machining",
                "pre_drill_chip_escape_holes"
            ],
            "threshold": 6.0
        },
        {
            "affected_face_ids": [
                "13",
                "25",
                "26",
                "27",
                "28",
                "29",
                "30",
                "31",
                "32"
            ],
            "location": {
                "x": 0.0,
                "y": 0.0,
                "z": 0.0
            },
            "measured_value": 100.52941176470588,
            "message": "型腔深度170.90mm，最小宽度1.70mm，深宽比100.53大于硬阈值6.00",
            "rule_id": "MILL_DEEP_POCKET",
            "rule_name": "深腔",
            "severity": "red",
            "suggestions": [
                "reduce_depth",
                "increase_opening_width",
                "use_stepdown_machining",
                "pre_drill_chip_escape_holes"
            ],
            "threshold": 6.0
        },
        {
            "affected_face_ids": [
                "42",
                "43",
                "44",
                "45",
                "46",
                "47",
                "48",
                "49"
            ],
            "location": {
                "x": 85.44999999999997,
                "y": 2.95,
                "z": -85.45
            },
            "measured_value": 152.50000020000013,
            "message": "Pocket[ClosedPocket_L1.7_W159_D159]内凸台高度152.50mm，超过允许高度24.00mm",
            "rule_id": "MILL_HIGH_BOSS",
            "rule_name": "高凸台（绝对高度）",
            "severity": "red",
            "suggestions": [
                "reduce_boss_height",
                "consider_multi_setup",
                "use_specialized_tooling"
            ],
            "threshold": 24.0
        },
        {
            "affected_face_ids": [
                "42",
                "43",
                "44",
                "45",
                "46",
                "47",
                "48",
                "49"
            ],
            "location": {
                "x": 85.44999999999997,
                "y": 2.95,
                "z": -85.45
            },
            "measured_value": 89.70587191695633,
            "message": "Pocket[ClosedPocket_L1.7_W159_D159]内凸台高宽比89.71，超过硬阈值3.00",
            "rule_id": "MILL_HIGH_BOSS",
            "rule_name": "高凸台（高宽比）",
            "severity": "red",
            "suggestions": [
                "reduce_boss_height",
                "increase_base_width",
                "consider_multi_setup",
                "use_specialized_tooling"
            ],
            "threshold": 3.0
        },
        {
            "affected_face_ids": [
                "25",
                "26",
                "27",
                "28",
                "29",
                "30",
                "31",
                "32"
            ],
            "location": {
                "x": 85.44999999999997,
                "y": 2.95,
                "z": -85.45
            },
            "measured_value": 163.00000020000007,
            "message": "Pocket[OpenPocket_L1.7_W170.9_D170.9]内凸台高度163.00mm，超过允许高度24.00mm",
            "rule_id": "MILL_HIGH_BOSS",
            "rule_name": "高凸台（绝对高度）",
            "severity": "red",
            "suggestions": [
                "reduce_boss_height",
                "consider_multi_setup",
                "use_specialized_tooling"
            ],
            "threshold": 24.0
        },
        {
            "affected_face_ids": [
                "25",
                "26",
                "27",
                "28",
                "29",
                "30",
                "31",
                "32"
            ],
            "location": {
                "x": 85.44999999999997,
                "y": 2.95,
                "z": -85.45
            },
            "measured_value": 95.88234177854808,
            "message": "Pocket[OpenPocket_L1.7_W170.9_D170.9]内凸台高宽比95.88，超过硬阈值3.00",
            "rule_id": "MILL_HIGH_BOSS",
            "rule_name": "高凸台（高宽比）",
            "severity": "red",
            "suggestions": [
                "reduce_boss_height",
                "increase_base_width",
                "consider_multi_setup",
                "use_specialized_tooling"
            ],
            "threshold": 3.0
        }
    ]
}
