{
    "version": "1",
    "parts": [
        {
            "partId": "part-001",
            "partName": "CNC_Part",
            "geometricProperties": {
                "volume": "160941.73",
                "surfaceArea": "117826.10",
                "AABB": {
                    "dimensions": {
                        "x": "300.00",
                        "y": "170.00",
                        "z": "10.00"
                    },
                    "minCorner": {
                        "x": "-0.00",
                        "y": "-0.00",
                        "z": "-0.00"
                    },
                    "maxCorner": {
                        "x": "300.00",
                        "y": "170.00",
                        "z": "10.00"
                    }
                }
            },
            "process": "CNC Machining Milling",
            "featureRecognition": {
                "name": "Feature Recognition",
                "totalFeatureCount": "153",
                "featureGroups": [
                    {
                        "name": "Flat Face Milled Face(s)",
                        "color": "(115, 251, 253)",
                        "totalGroupFeatureCount": "45",
                        "featureCount": "45",
                        "features": [
                            {
                                "shapeIDCount": "1",
                                "shapeIDs": [
                                    {
                                        "id": "3"
                                    }
                                ]
                            },
                            {
                                "shapeIDCount": "1",
                                "shapeIDs": [
                                    {
                                        "id": "10"
                                    }
                                ]
                            },
                            {
                                "shapeIDCount": "1",
                                "shapeIDs": [
                                    {
                                        "id": "12"
                                    }
                                ]
                            },
                            {
                                "shapeIDCount": "1",
                                "shapeIDs": [
                                    {
                                        "id": "14"
                                    }
                                ]
                            },
                            {
                                "shapeIDCount": "1",
                                "shapeIDs": [
                                    {
                                        "id": "16"
                                    }
                                ]
                            },
                            {
                                "shapeIDCount": "1",
                                "shapeIDs": [
                                    {
                                        "id": "18"
                                    }
                                ]
                            },
                            {
                                "shapeIDCount": "1",
                                "shapeIDs": [
                                    {
                                        "id": "20"
                                    }
                                ]
                            },
                            {
                                "shapeIDCount": "1",
                                "shapeIDs": [
                                    {
                                        "id": "22"
                                    }
                                ]
                            },
                            {
                                "shapeIDCount": "1",
                                "shapeIDs": [
                                    {
                                        "id": "24"
                                    }
                                ]
                            },
                            {
                                "shapeIDCount": "1",
                                "shapeIDs": [
                                    {
                                        "id": "26"
                                    }
                                ]
                            },
                            {
                                "shapeIDCount": "1",
                                "shapeIDs": [
                                    {
                                        "id": "28"
                                    }
                                ]
                            },
                            {
                                "shapeIDCount": "1",
                                "shapeIDs": [
                                    {
                                        "id": "30"
                                    }
                                ]
                            },
                            {
                                "shapeIDCount": "1",
                                "shapeIDs": [
                                    {
                                        "id": "32"
                                    }
                                ]
                            },
                            {
                                "shapeIDCount": "1",
                                "shapeIDs": [
                                    {
                                        "id": "34"
                                    }
                                ]
                            },
                            {
                                "shapeIDCount": "1",
                                "shapeIDs": [
                                    {
                                        "id": "36"
                                    }
                                ]
                            },
                            {
                                "shapeIDCount": "1",
                                "shapeIDs": [
                                    {
                                        "id": "38"
                                    }
                                ]
                            },
                            {
                                "shapeIDCount": "1",
                                "shapeIDs": [
                                    {
                                        "id": "40"
                                    }
                                ]
                            },
                            {
                                "shapeIDCount": "1",
                                "shapeIDs": [
                                    {
                                        "id": "42"
                                    }
                                ]
                            },
                            {
                                "shapeIDCount": "1",
                                "shapeIDs": [
                                    {
                                        "id": "44"
                                    }
                                ]
                            },
                            {
                                "shapeIDCount": "1",
                                "shapeIDs": [
                                    {
                                        "id": "46"
                                    }
                                ]
                            },
                            {
                                "shapeIDCount": "1",
                                "shapeIDs": [
                                    {
                                        "id": "48"
                                    }
                                ]
                            },
                            {
                                "shapeIDCount": "1",
                                "shapeIDs": [
                                    {
                                        "id": "50"
                                    }
                                ]
                            },
                            {
                                "shapeIDCount": "1",
                                "shapeIDs": [
                                    {
                                        "id": "52"
                                    }
                                ]
                            },
                            {
                                "shapeIDCount": "1",
                                "shapeIDs": [
                                    {
                                        "id": "54"
                                    }
                                ]
                            },
                            {
                                "shapeIDCount": "1",
                                "shapeIDs": [
                                    {
                                        "id": "56"
                                    }
                                ]
                            },
                            {
                                "shapeIDCount": "1",
                                "shapeIDs": [
                                    {
                                        "id": "58"
                                    }
                                ]
                            },
                            {
                                "shapeIDCount": "1",
                                "shapeIDs": [
                                    {
                                        "id": "60"
                                    }
                                ]
                            },
                            {
                                "shapeIDCount": "1",
                                "shapeIDs": [
                                    {
                                        "id": "62"
                                    }
                                ]
                            },
                            {
                                "shapeIDCount": "1",
                                "shapeIDs": [
                                    {
                                        "id": "64"
                                    }
                                ]
                            },
                            {
                                "shapeIDCount": "1",
                                "shapeIDs": [
                                    {
                                        "id": "66"
                                    }
                                ]
                            },
                            {
                                "shapeIDCount": "1",
                                "shapeIDs": [
                                    {
                                        "id": "68"
                                    }
                                ]
                            },
                            {
                                "shapeIDCount": "1",
                                "shapeIDs": [
                                    {
                                        "id": "70"
                                    }
                                ]
                            },
                            {
                                "shapeIDCount": "1",
                                "shapeIDs": [
                                    {
                                        "id": "72"
                                    }
                                ]
                            },
                            {
                                "shapeIDCount": "1",
                                "shapeIDs": [
                                    {
                                        "id": "74"
                                    }
                                ]
                            },
                            {
                                "shapeIDCount": "1",
                                "shapeIDs": [
                                    {
                                        "id": "76"
                                    }
                                ]
                            },
                            {
                                "shapeIDCount": "1",
                                "shapeIDs": [
                                    {
                                        "id": "78"
                                    }
                                ]
                            },
                            {
                                "shapeIDCount": "1",
                                "shapeIDs": [
                                    {
                                        "id": "80"
                                    }
                                ]
                            },
                            {
                                "shapeIDCount": "1",
                                "shapeIDs": [
                                    {
                                        "id": "82"
                                    }
                                ]
                            },
                            {
                                "shapeIDCount": "1",
                                "shapeIDs": [
                                    {
                                        "id": "84"
                                    }
                                ]
                            },
                            {
                                "shapeIDCount": "1",
                                "shapeIDs": [
                                    {
                                        "id": "86"
                                    }
                                ]
                            },
                            {
                                "shapeIDCount": "1",
                                "shapeIDs": [
                                    {
                                        "id": "88"
                                    }
                                ]
                            },
                            {
                                "shapeIDCount": "1",
                                "shapeIDs": [
                                    {
                                        "id": "277"
                                    }
                                ]
                            },
                            {
                                "shapeIDCount": "1",
                                "shapeIDs": [
                                    {
                                        "id": "281"
                                    }
                                ]
                            },
                            {
                                "shapeIDCount": "1",
                                "shapeIDs": [
                                    {
                                        "id": "285"
                                    }
                                ]
                            },
                            {
                                "shapeIDCount": "1",
                                "shapeIDs": [
                                    {
                                        "id": "288"
                                    }
                                ]
                            }
                        ]
                    },
                    {
                        "name": "Blind Hole(s)",
                        "color": "(200, 100, 100)",
                        "totalGroupFeatureCount": "30",
                        "subGroupCount": "1",
                        "subGroups": [
                            {
                                "parametersCount": "3",
                                "parameters": [
                                    {
                                        "name": "Radius",
                                        "units": "mm",
                                        "value": "3.000000"
                                    },
                                    {
                                        "name": "Depth",
                                        "units": "mm",
                                        "value": "1.500000"
                                    },
                                    {
                                        "name": "Axis",
                                        "units": "",
                                        "value": "(0.00, 0.00, 1.00)"
                                    }
                                ],
                                "featureCount": "30",
                        "features": [
                            {
                                "shapeIDCount": "2",
                                "shapeIDs": [
                                    {
                                        "id": "150"
                                    },
                                    {
                                        "id": "149"
                                    }
                                ]
                            },
                            {
                                "shapeIDCount": "2",
                                "shapeIDs": [
                                    {
                                        "id": "152"
                                    },
                                    {
                                        "id": "151"
                                    }
                                ]
                            },
                            {
                                "shapeIDCount": "2",
                                "shapeIDs": [
                                    {
                                        "id": "154"
                                    },
                                    {
                                        "id": "153"
                                    }
                                ]
                            },
                            {
                                "shapeIDCount": "2",
                                "shapeIDs": [
                                    {
                                        "id": "156"
                                    },
                                    {
                                        "id": "155"
                                    }
                                ]
                            },
                            {
                                "shapeIDCount": "2",
                                "shapeIDs": [
                                    {
                                        "id": "158"
                                    },
                                    {
                                        "id": "157"
                                    }
                                ]
                            },
                            {
                                "shapeIDCount": "2",
                                "shapeIDs": [
                                    {
                                        "id": "160"
                                    },
                                    {
                                        "id": "159"
                                    }
                                ]
                            },
                            {
                                "shapeIDCount": "2",
                                "shapeIDs": [
                                    {
                                        "id": "162"
                                    },
                                    {
                                        "id": "161"
                                    }
                                ]
                            },
                            {
                                "shapeIDCount": "2",
                                "shapeIDs": [
                                    {
                                        "id": "164"
                                    },
                                    {
                                        "id": "163"
                                    }
                                ]
                            },
                            {
                                "shapeIDCount": "2",
                                "shapeIDs": [
                                    {
                                        "id": "166"
                                    },
                                    {
                                        "id": "165"
                                    }
                                ]
                            },
                            {
                                "shapeIDCount": "2",
                                "shapeIDs": [
                                    {
                                        "id": "168"
                                    },
                                    {
                                        "id": "167"
                                    }
                                ]
                            },
                            {
                                "shapeIDCount": "2",
                                "shapeIDs": [
                                    {
                                        "id": "170"
                                    },
                                    {
                                        "id": "169"
                                    }
                                ]
                            },
                            {
                                "shapeIDCount": "2",
                                "shapeIDs": [
                                    {
                                        "id": "172"
                                    },
                                    {
                                        "id": "171"
                                    }
                                ]
                            },
                            {
                                "shapeIDCount": "2",
                                "shapeIDs": [
                                    {
                                        "id": "174"
                                    },
                                    {
                                        "id": "173"
                                    }
                                ]
                            },
                            {
                                "shapeIDCount": "2",
                                "shapeIDs": [
                                    {
                                        "id": "176"
                                    },
                                    {
                                        "id": "175"
                                    }
                                ]
                            },
                            {
                                "shapeIDCount": "2",
                                "shapeIDs": [
                                    {
                                        "id": "178"
                                    },
                                    {
                                        "id": "177"
                                    }
                                ]
                            },
                            {
                                "shapeIDCount": "2",
                                "shapeIDs": [
                                    {
                                        "id": "180"
                                    },
                                    {
                                        "id": "179"
                                    }
                                ]
                            },
                            {
                                "shapeIDCount": "2",
                                "shapeIDs": [
                                    {
                                        "id": "182"
                                    },
                                    {
                                        "id": "181"
                                    }
                                ]
                            },
                            {
                                "shapeIDCount": "2",
                                "shapeIDs": [
                                    {
                                        "id": "184"
                                    },
                                    {
                                        "id": "183"
                                    }
                                ]
                            },
                            {
                                "shapeIDCount": "2",
                                "shapeIDs": [
                                    {
                                        "id": "186"
                                    },
                                    {
                                        "id": "185"
                                    }
                                ]
                            },
                            {
                                "shapeIDCount": "2",
                                "shapeIDs": [
                                    {
                                        "id": "188"
                                    },
                                    {
                                        "id": "187"
                                    }
                                ]
                            },
                            {
                                "shapeIDCount": "2",
                                "shapeIDs": [
                                    {
                                        "id": "190"
                                    },
                                    {
                                        "id": "189"
                                    }
                                ]
                            },
                            {
                                "shapeIDCount": "2",
                                "shapeIDs": [
                                    {
                                        "id": "192"
                                    },
                                    {
                                        "id": "191"
                                    }
                                ]
                            },
                            {
                                "shapeIDCount": "2",
                                "shapeIDs": [
                                    {
                                        "id": "194"
                                    },
                                    {
                                        "id": "193"
                                    }
                                ]
                            },
                            {
                                "shapeIDCount": "2",
                                "shapeIDs": [
                                    {
                                        "id": "196"
                                    },
                                    {
                                        "id": "195"
                                    }
                                ]
                            },
                            {
                                "shapeIDCount": "2",
                                "shapeIDs": [
                                    {
                                        "id": "198"
                                    },
                                    {
                                        "id": "197"
                                    }
                                ]
                            },
                            {
                                "shapeIDCount": "2",
                                "shapeIDs": [
                                    {
                                        "id": "200"
                                    },
                                    {
                                        "id": "199"
                                    }
                                ]
                            },
                            {
                                "shapeIDCount": "2",
                                "shapeIDs": [
                                    {
                                        "id": "202"
                                    },
                                    {
                                        "id": "201"
                                    }
                                ]
                            },
                            {
                                "shapeIDCount": "2",
                                "shapeIDs": [
                                    {
                                        "id": "204"
                                    },
                                    {
                                        "id": "203"
                                    }
                                ]
                            },
                            {
                                "shapeIDCount": "2",
                                "shapeIDs": [
                                    {
                                        "id": "206"
                                    },
                                    {
                                        "id": "205"
                                    }
                                ]
                            },
                            {
                                "shapeIDCount": "2",
                                "shapeIDs": [
                                    {
                                        "id": "208"
                                    },
                                    {
                                        "id": "207"
                                    }
                                ]
                            }
                        ]
                            }
                        ]
                    },
                    {
                        "name": "Through Hole(s)",
                        "color": "(240, 135, 132)",
                        "totalGroupFeatureCount": "46",
                        "subGroupCount": "1",
                        "subGroups": [
                            {
                                "parametersCount": "3",
                                "parameters": [
                                    {
                                        "name": "Radius",
                                        "units": "mm",
                                        "value": "2.000000"
                                    },
                                    {
                                        "name": "Depth",
                                        "units": "mm",
                                        "value": "10.000000"
                                    },
                                    {
                                        "name": "Axis",
                                        "units": "",
                                        "value": "(0.00, 0.00, 1.00)"
                                    }
                                ],
                                "featureCount": "46",
                        "features": [
                            {
                                "shapeIDCount": "1",
                                "shapeIDs": [
                                    {
                                        "id": "229"
                                    }
                                ]
                            },
                            {
                                "shapeIDCount": "1",
                                "shapeIDs": [
                                    {
                                        "id": "230"
                                    }
                                ]
                            },
                            {
                                "shapeIDCount": "1",
                                "shapeIDs": [
                                    {
                                        "id": "231"
                                    }
                                ]
                            },
                            {
                                "shapeIDCount": "1",
                                "shapeIDs": [
                                    {
                                        "id": "232"
                                    }
                                ]
                            },
                            {
                                "shapeIDCount": "1",
                                "shapeIDs": [
                                    {
                                        "id": "233"
                                    }
                                ]
                            },
                            {
                                "shapeIDCount": "1",
                                "shapeIDs": [
                                    {
                                        "id": "234"
                                    }
                                ]
                            },
                            {
                                "shapeIDCount": "1",
                                "shapeIDs": [
                                    {
                                        "id": "235"
                                    }
                                ]
                            },
                            {
                                "shapeIDCount": "1",
                                "shapeIDs": [
                                    {
                                        "id": "236"
                                    }
                                ]
                            },
                            {
                                "shapeIDCount": "1",
                                "shapeIDs": [
                                    {
                                        "id": "237"
                                    }
                                ]
                            },
                            {
                                "shapeIDCount": "1",
                                "shapeIDs": [
                                    {
                                        "id": "238"
                                    }
                                ]
                            },
                            {
                                "shapeIDCount": "1",
                                "shapeIDs": [
                                    {
                                        "id": "239"
                                    }
                                ]
                            },
                            {
                                "shapeIDCount": "1",
                                "shapeIDs": [
                                    {
                                        "id": "240"
                                    }
                                ]
                            },
                            {
                                "shapeIDCount": "1",
                                "shapeIDs": [
                                    {
                                        "id": "241"
                                    }
                                ]
                            },
                            {
                                "shapeIDCount": "1",
                                "shapeIDs": [
                                    {
                                        "id": "242"
                                    }
                                ]
                            },
                            {
                                "shapeIDCount": "1",
                                "shapeIDs": [
                                    {
                                        "id": "243"
                                    }
                                ]
                            },
                            {
                                "shapeIDCount": "1",
                                "shapeIDs": [
                                    {
                                        "id": "244"
                                    }
                                ]
                            },
                            {
                                "shapeIDCount": "1",
                                "shapeIDs": [
                                    {
                                        "id": "245"
                                    }
                                ]
                            },
                            {
                                "shapeIDCount": "1",
                                "shapeIDs": [
                                    {
                                        "id": "246"
                                    }
                                ]
                            },
                            {
                                "shapeIDCount": "1",
                                "shapeIDs": [
                                    {
                                        "id": "247"
                                    }
                                ]
                            },
                            {
                                "shapeIDCount": "1",
                                "shapeIDs": [
                                    {
                                        "id": "248"
                                    }
                                ]
                            },
                            {
                                "shapeIDCount": "1",
                                "shapeIDs": [
                                    {
                                        "id": "249"
                                    }
                                ]
                            },
                            {
                                "shapeIDCount": "1",
                                "shapeIDs": [
                                    {
                                        "id": "250"
                                    }
                                ]
                            },
                            {
                                "shapeIDCount": "1",
                                "shapeIDs": [
                                    {
                                        "id": "251"
                                    }
                                ]
                            },
                            {
                                "shapeIDCount": "1",
                                "shapeIDs": [
                                    {
                                        "id": "252"
                                    }
                                ]
                            },
                            {
                                "shapeIDCount": "1",
                                "shapeIDs": [
                                    {
                                        "id": "253"
                                    }
                                ]
                            },
                            {
                                "shapeIDCount": "1",
                                "shapeIDs": [
                                    {
                                        "id": "254"
                                    }
                                ]
                            },
                            {
                                "shapeIDCount": "1",
                                "shapeIDs": [
                                    {
                                        "id": "255"
                                    }
                                ]
                            },
                            {
                                "shapeIDCount": "1",
                                "shapeIDs": [
                                    {
                                        "id": "256"
                                    }
                                ]
                            },
                            {
                                "shapeIDCount": "1",
                                "shapeIDs": [
                                    {
                                        "id": "257"
                                    }
                                ]
                            },
                            {
                                "shapeIDCount": "1",
                                "shapeIDs": [
                                    {
                                        "id": "258"
                                    }
                                ]
                            },
                            {
                                "shapeIDCount": "1",
                                "shapeIDs": [
                                    {
                                        "id": "259"
                                    }
                                ]
                            },
                            {
                                "shapeIDCount": "1",
                                "shapeIDs": [
                                    {
                                        "id": "260"
                                    }
                                ]
                            },
                            {
                                "shapeIDCount": "1",
                                "shapeIDs": [
                                    {
                                        "id": "261"
                                    }
                                ]
                            },
                            {
                                "shapeIDCount": "1",
                                "shapeIDs": [
                                    {
                                        "id": "262"
                                    }
                                ]
                            },
                            {
                                "shapeIDCount": "1",
                                "shapeIDs": [
                                    {
                                        "id": "263"
                                    }
                                ]
                            },
                            {
                                "shapeIDCount": "1",
                                "shapeIDs": [
                                    {
                                        "id": "264"
                                    }
                                ]
                            },
                            {
                                "shapeIDCount": "1",
                                "shapeIDs": [
                                    {
                                        "id": "265"
                                    }
                                ]
                            },
                            {
                                "shapeIDCount": "1",
                                "shapeIDs": [
                                    {
                                        "id": "266"
                                    }
                                ]
                            },
                            {
                                "shapeIDCount": "1",
                                "shapeIDs": [
                                    {
                                        "id": "267"
                                    }
                                ]
                            },
                            {
                                "shapeIDCount": "1",
                                "shapeIDs": [
                                    {
                                        "id": "268"
                                    }
                                ]
                            },
                            {
                                "shapeIDCount": "1",
                                "shapeIDs": [
                                    {
                                        "id": "269"
                                    }
                                ]
                            },
                            {
                                "shapeIDCount": "1",
                                "shapeIDs": [
                                    {
                                        "id": "270"
                                    }
                                ]
                            },
                            {
                                "shapeIDCount": "1",
                                "shapeIDs": [
                                    {
                                        "id": "271"
                                    }
                                ]
                            },
                            {
                                "shapeIDCount": "1",
                                "shapeIDs": [
                                    {
                                        "id": "272"
                                    }
                                ]
                            },
                            {
                                "shapeIDCount": "1",
                                "shapeIDs": [
                                    {
                                        "id": "273"
                                    }
                                ]
                            },
                            {
                                "shapeIDCount": "1",
                                "shapeIDs": [
                                    {
                                        "id": "274"
                                    }
                                ]
                            }
                        ]
                            }
                        ]
                    },
                    {
                        "name": "Open Pocket(s)",
                        "color": "(120, 60, 30)",
                        "totalGroupFeatureCount": "31",
                        "subGroupCount": "1",
                        "subGroups": [
                            {
                                "parametersCount": "4",
                                "parameters": [
                                    {
                                        "name": "Length",
                                        "units": "mm",
                                        "value": "170.000000"
                                    },
                                    {
                                        "name": "Width",
                                        "units": "mm",
                                        "value": "300.000000"
                                    },
                                    {
                                        "name": "Depth",
                                        "units": "mm",
                                        "value": "7.000000"
                                    },
                                    {
                                        "name": "Axis",
                                        "units": "",
                                        "value": "(0.00, 0.00, -1.00)"
                                    }
                                ],
                                "featureCount": "31",
                        "features": [
                            {
                                "shapeIDCount": "47",
                                "shapeIDs": [
                                    {
                                        "id": "4"
                                    },
                                    {
                                        "id": "275"
                                    },
                                    {
                                        "id": "278"
                                    },
                                    {
                                        "id": "286"
                                    },
                                    {
                                        "id": "280"
                                    },
                                    {
                                        "id": "282"
                                    },
                                    {
                                        "id": "284"
                                    },
                                    {
                                        "id": "9"
                                    },
                                    {
                                        "id": "11"
                                    },
                                    {
                                        "id": "13"
                                    },
                                    {
                                        "id": "15"
                                    },
                                    {
                                        "id": "17"
                                    },
                                    {
                                        "id": "19"
                                    },
                                    {
                                        "id": "21"
                                    },
                                    {
                                        "id": "23"
                                    },
                                    {
                                        "id": "25"
                                    },
                                    {
                                        "id": "27"
                                    },
                                    {
                                        "id": "29"
                                    },
                                    {
                                        "id": "31"
                                    },
                                    {
                                        "id": "33"
                                    },
                                    {
                                        "id": "35"
                                    },
                                    {
                                        "id": "37"
                                    },
                                    {
                                        "id": "39"
                                    },
                                    {
                                        "id": "41"
                                    },
                                    {
                                        "id": "43"
                                    },
                                    {
                                        "id": "45"
                                    },
                                    {
                                        "id": "47"
                                    },
                                    {
                                        "id": "49"
                                    },
                                    {
                                        "id": "51"
                                    },
                                    {
                                        "id": "53"
                                    },
                                    {
                                        "id": "55"
                                    },
                                    {
                                        "id": "57"
                                    },
                                    {
                                        "id": "59"
                                    },
                                    {
                                        "id": "61"
                                    },
                                    {
                                        "id": "63"
                                    },
                                    {
                                        "id": "65"
                                    },
                                    {
                                        "id": "67"
                                    },
                                    {
                                        "id": "69"
                                    },
                                    {
                                        "id": "71"
                                    },
                                    {
                                        "id": "73"
                                    },
                                    {
                                        "id": "75"
                                    },
                                    {
                                        "id": "77"
                                    },
                                    {
                                        "id": "79"
                                    },
                                    {
                                        "id": "81"
                                    },
                                    {
                                        "id": "83"
                                    },
                                    {
                                        "id": "85"
                                    },
                                    {
                                        "id": "87"
                                    }
                                ],
                                "bossesIDs": ["9", "11", "13", "15", "17", "19", "21", "23", "25", "27", "29", "31", "33", "35", "37", "39", "41", "43", "45", "47", "49", "51", "53", "55", "57", "59", "61", "63", "65", "67", "69", "71", "73", "75", "77", "79", "81", "83", "85", "87"]
                            },
                            {
                                "shapeIDCount": "3",
                                "shapeIDs": [
                                    {
                                        "id": "123"
                                    },
                                    {
                                        "id": "122"
                                    },
                                    {
                                        "id": "124"
                                    }
                                ]
                            },
                            {
                                "shapeIDCount": "3",
                                "shapeIDs": [
                                    {
                                        "id": "140"
                                    },
                                    {
                                        "id": "141"
                                    },
                                    {
                                        "id": "142"
                                    }
                                ]
                            },
                            {
                                "shapeIDCount": "3",
                                "shapeIDs": [
                                    {
                                        "id": "137"
                                    },
                                    {
                                        "id": "138"
                                    },
                                    {
                                        "id": "139"
                                    }
                                ]
                            },
                            {
                                "shapeIDCount": "3",
                                "shapeIDs": [
                                    {
                                        "id": "113"
                                    },
                                    {
                                        "id": "114"
                                    },
                                    {
                                        "id": "115"
                                    }
                                ]
                            },
                            {
                                "shapeIDCount": "3",
                                "shapeIDs": [
                                    {
                                        "id": "104"
                                    },
                                    {
                                        "id": "105"
                                    },
                                    {
                                        "id": "106"
                                    }
                                ]
                            },
                            {
                                "shapeIDCount": "3",
                                "shapeIDs": [
                                    {
                                        "id": "101"
                                    },
                                    {
                                        "id": "102"
                                    },
                                    {
                                        "id": "103"
                                    }
                                ]
                            },
                            {
                                "shapeIDCount": "3",
                                "shapeIDs": [
                                    {
                                        "id": "116"
                                    },
                                    {
                                        "id": "117"
                                    },
                                    {
                                        "id": "118"
                                    }
                                ]
                            },
                            {
                                "shapeIDCount": "3",
                                "shapeIDs": [
                                    {
                                        "id": "92"
                                    },
                                    {
                                        "id": "93"
                                    },
                                    {
                                        "id": "94"
                                    }
                                ]
                            },
                            {
                                "shapeIDCount": "3",
                                "shapeIDs": [
                                    {
                                        "id": "89"
                                    },
                                    {
                                        "id": "90"
                                    },
                                    {
                                        "id": "91"
                                    }
                                ]
                            },
                            {
                                "shapeIDCount": "3",
                                "shapeIDs": [
                                    {
                                        "id": "132"
                                    },
                                    {
                                        "id": "131"
                                    },
                                    {
                                        "id": "133"
                                    }
                                ]
                            },
                            {
                                "shapeIDCount": "3",
                                "shapeIDs": [
                                    {
                                        "id": "135"
                                    },
                                    {
                                        "id": "134"
                                    },
                                    {
                                        "id": "136"
                                    }
                                ]
                            },
                            {
                                "shapeIDCount": "3",
                                "shapeIDs": [
                                    {
                                        "id": "147"
                                    },
                                    {
                                        "id": "146"
                                    },
                                    {
                                        "id": "148"
                                    }
                                ]
                            },
                            {
                                "shapeIDCount": "3",
                                "shapeIDs": [
                                    {
                                        "id": "144"
                                    },
                                    {
                                        "id": "143"
                                    },
                                    {
                                        "id": "145"
                                    }
                                ]
                            },
                            {
                                "shapeIDCount": "3",
                                "shapeIDs": [
                                    {
                                        "id": "125"
                                    },
                                    {
                                        "id": "126"
                                    },
                                    {
                                        "id": "127"
                                    }
                                ]
                            },
                            {
                                "shapeIDCount": "3",
                                "shapeIDs": [
                                    {
                                        "id": "128"
                                    },
                                    {
                                        "id": "129"
                                    },
                                    {
                                        "id": "130"
                                    }
                                ]
                            },
                            {
                                "shapeIDCount": "3",
                                "shapeIDs": [
                                    {
                                        "id": "96"
                                    },
                                    {
                                        "id": "95"
                                    },
                                    {
                                        "id": "97"
                                    }
                                ]
                            },
                            {
                                "shapeIDCount": "3",
                                "shapeIDs": [
                                    {
                                        "id": "99"
                                    },
                                    {
                                        "id": "98"
                                    },
                                    {
                                        "id": "100"
                                    }
                                ]
                            },
                            {
                                "shapeIDCount": "3",
                                "shapeIDs": [
                                    {
                                        "id": "108"
                                    },
                                    {
                                        "id": "107"
                                    },
                                    {
                                        "id": "109"
                                    }
                                ]
                            },
                            {
                                "shapeIDCount": "3",
                                "shapeIDs": [
                                    {
                                        "id": "111"
                                    },
                                    {
                                        "id": "110"
                                    },
                                    {
                                        "id": "112"
                                    }
                                ]
                            },
                            {
                                "shapeIDCount": "3",
                                "shapeIDs": [
                                    {
                                        "id": "120"
                                    },
                                    {
                                        "id": "119"
                                    },
                                    {
                                        "id": "121"
                                    }
                                ]
                            },
                            {
                                "shapeIDCount": "2",
                                "shapeIDs": [
                                    {
                                        "id": "225"
                                    },
                                    {
                                        "id": "226"
                                    }
                                ]
                            },
                            {
                                "shapeIDCount": "2",
                                "shapeIDs": [
                                    {
                                        "id": "221"
                                    },
                                    {
                                        "id": "222"
                                    }
                                ]
                            },
                            {
                                "shapeIDCount": "2",
                                "shapeIDs": [
                                    {
                                        "id": "217"
                                    },
                                    {
                                        "id": "218"
                                    }
                                ]
                            },
                            {
                                "shapeIDCount": "2",
                                "shapeIDs": [
                                    {
                                        "id": "213"
                                    },
                                    {
                                        "id": "214"
                                    }
                                ]
                            },
                            {
                                "shapeIDCount": "2",
                                "shapeIDs": [
                                    {
                                        "id": "209"
                                    },
                                    {
                                        "id": "210"
                                    }
                                ]
                            },
                            {
                                "shapeIDCount": "2",
                                "shapeIDs": [
                                    {
                                        "id": "216"
                                    },
                                    {
                                        "id": "215"
                                    }
                                ]
                            },
                            {
                                "shapeIDCount": "2",
                                "shapeIDs": [
                                    {
                                        "id": "212"
                                    },
                                    {
                                        "id": "211"
                                    }
                                ]
                            },
                            {
                                "shapeIDCount": "2",
                                "shapeIDs": [
                                    {
                                        "id": "220"
                                    },
                                    {
                                        "id": "219"
                                    }
                                ]
                            },
                            {
                                "shapeIDCount": "2",
                                "shapeIDs": [
                                    {
                                        "id": "224"
                                    },
                                    {
                                        "id": "223"
                                    }
                                ]
                            },
                            {
                                "shapeIDCount": "2",
                                "shapeIDs": [
                                    {
                                        "id": "228"
                                    },
                                    {
                                        "id": "227"
                                    }
                                ]
                            }
                        ]
                            }
                        ]
                    },
                    {
                        "name": "Profile Feature(s)",
                        "color": "(0, 200, 100)",
                        "totalGroupFeatureCount": "1",
                        "featureCount": "1",
                        "features": [
                            {
                                "shapeIDCount": "12",
                                "shapeIDs": [
                                    {
                                        "id": "1"
                                    },
                                    {
                                        "id": "279"
                                    },
                                    {
                                        "id": "290"
                                    },
                                    {
                                        "id": "276"
                                    },
                                    {
                                        "id": "6"
                                    },
                                    {
                                        "id": "7"
                                    },
                                    {
                                        "id": "8"
                                    },
                                    {
                                        "id": "5"
                                    },
                                    {
                                        "id": "2"
                                    },
                                    {
                                        "id": "287"
                                    },
                                    {
                                        "id": "289"
                                    },
                                    {
                                        "id": "283"
                                    }
                                ]
                            }
                        ]
                    }
                ]
            }
        }
    ]
}