{
    "version": "1",
    "parts": [
        {
            "partId": "part-001",
            "partName": "CNC_Part",
            "geometricProperties": {
                "volume": "8276.72",
                "surfaceArea": "11705.99",
                "AABB": {
                    "dimensions": {
                        "x": "70.00",
                        "y": "99.00",
                        "z": "4.50"
                    },
                    "minCorner": {
                        "x": "-40.00",
                        "y": "-261.00",
                        "z": "-4.00"
                    },
                    "maxCorner": {
                        "x": "30.00",
                        "y": "-162.00",
                        "z": "0.50"
                    }
                }
            },
            "process": "CNC Machining Milling",
            "featureRecognition": {
                "name": "Feature Recognition",
                "totalFeatureCount": "15",
                "featureGroups": [
                    {
                        "name": "Flat Face Milled Face(s)",
                        "color": "(115, 251, 253)",
                        "totalGroupFeatureCount": "7",
                        "featureCount": "7",
                        "features": [
                            {
                                "shapeIDCount": "1",
                                "shapeIDs": [
                                    {
                                        "id": "47"
                                    }
                                ]
                            },
                            {
                                "shapeIDCount": "1",
                                "shapeIDs": [
                                    {
                                        "id": "67"
                                    }
                                ]
                            },
                            {
                                "shapeIDCount": "1",
                                "shapeIDs": [
                                    {
                                        "id": "69"
                                    }
                                ]
                            },
                            {
                                "shapeIDCount": "1",
                                "shapeIDs": [
                                    {
                                        "id": "96"
                                    }
                                ]
                            },
                            {
                                "shapeIDCount": "1",
                                "shapeIDs": [
                                    {
                                        "id": "115"
                                    }
                                ]
                            },
                            {
                                "shapeIDCount": "1",
                                "shapeIDs": [
                                    {
                                        "id": "118"
                                    }
                                ]
                            },
                            {
                                "shapeIDCount": "1",
                                "shapeIDs": [
                                    {
                                        "id": "120"
                                    }
                                ]
                            }
                        ]
                    },
                    {
                        "name": "Open Pocket(s)",
                        "color": "(120, 60, 30)",
                        "totalGroupFeatureCount": "7",
                        "subGroupCount": "1",
                        "subGroups": [
                            {
                                "parametersCount": "4",
                                "parameters": [
                                    {
                                        "name": "Length",
                                        "units": "mm",
                                        "value": "99.000000"
                                    },
                                    {
                                        "name": "Width",
                                        "units": "mm",
                                        "value": "70.000000"
                                    },
                                    {
                                        "name": "Depth",
                                        "units": "mm",
                                        "value": "4.000000"
                                    },
                                    {
                                        "name": "Axis",
                                        "units": "",
                                        "value": "(0.00, 0.00, -1.00)"
                                    }
                                ],
                                "featureCount": "7",
                        "features": [
                            {
                                "shapeIDCount": "15",
                                "shapeIDs": [
                                    {
                                        "id": "80"
                                    },
                                    {
                                        "id": "56"
                                    },
                                    {
                                        "id": "144"
                                    },
                                    {
                                        "id": "82"
                                    },
                                    {
                                        "id": "58"
                                    },
                                    {
                                        "id": "68"
                                    },
                                    {
                                        "id": "71"
                                    },
                                    {
                                        "id": "83"
                                    },
                                    {
                                        "id": "94"
                                    },
                                    {
                                        "id": "158"
                                    },
                                    {
                                        "id": "103"
                                    },
                                    {
                                        "id": "104"
                                    },
                                    {
                                        "id": "116"
                                    },
                                    {
                                        "id": "151"
                                    },
                                    {
                                        "id": "159"
                                    }
                                ]
                            },
                            {
                                "shapeIDCount": "12",
                                "shapeIDs": [
                                    {
                                        "id": "57"
                                    },
                                    {
                                        "id": "61"
                                    },
                                    {
                                        "id": "37"
                                    },
                                    {
                                        "id": "62"
                                    },
                                    {
                                        "id": "38"
                                    },
                                    {
                                        "id": "39"
                                    },
                                    {
                                        "id": "40"
                                    },
                                    {
                                        "id": "60"
                                    },
                                    {
                                        "id": "63"
                                    },
                                    {
                                        "id": "64"
                                    },
                                    {
                                        "id": "65"
                                    },
                                    {
                                        "id": "66"
                                    }
                                ]
                            },
                            {
                                "shapeIDCount": "12",
                                "shapeIDs": [
                                    {
                                        "id": "78"
                                    },
                                    {
                                        "id": "70"
                                    },
                                    {
                                        "id": "73"
                                    },
                                    {
                                        "id": "33"
                                    },
                                    {
                                        "id": "34"
                                    },
                                    {
                                        "id": "35"
                                    },
                                    {
                                        "id": "36"
                                    },
                                    {
                                        "id": "72"
                                    },
                                    {
                                        "id": "74"
                                    },
                                    {
                                        "id": "75"
                                    },
                                    {
                                        "id": "76"
                                    },
                                    {
                                        "id": "77"
                                    }
                                ]
                            },
                            {
                                "shapeIDCount": "12",
                                "shapeIDs": [
                                    {
                                        "id": "87"
                                    },
                                    {
                                        "id": "31"
                                    },
                                    {
                                        "id": "95"
                                    },
                                    {
                                        "id": "29"
                                    },
                                    {
                                        "id": "93"
                                    },
                                    {
                                        "id": "30"
                                    },
                                    {
                                        "id": "88"
                                    },
                                    {
                                        "id": "32"
                                    },
                                    {
                                        "id": "89"
                                    },
                                    {
                                        "id": "90"
                                    },
                                    {
                                        "id": "91"
                                    },
                                    {
                                        "id": "92"
                                    }
                                ]
                            },
                            {
                                "shapeIDCount": "12",
                                "shapeIDs": [
                                    {
                                        "id": "153"
                                    },
                                    {
                                        "id": "145"
                                    },
                                    {
                                        "id": "1"
                                    },
                                    {
                                        "id": "146"
                                    },
                                    {
                                        "id": "18"
                                    },
                                    {
                                        "id": "2"
                                    },
                                    {
                                        "id": "3"
                                    },
                                    {
                                        "id": "119"
                                    },
                                    {
                                        "id": "147"
                                    },
                                    {
                                        "id": "148"
                                    },
                                    {
                                        "id": "149"
                                    },
                                    {
                                        "id": "150"
                                    }
                                ]
                            },
                            {
                                "shapeIDCount": "12",
                                "shapeIDs": [
                                    {
                                        "id": "152"
                                    },
                                    {
                                        "id": "4"
                                    },
                                    {
                                        "id": "5"
                                    },
                                    {
                                        "id": "6"
                                    },
                                    {
                                        "id": "121"
                                    },
                                    {
                                        "id": "17"
                                    },
                                    {
                                        "id": "138"
                                    },
                                    {
                                        "id": "139"
                                    },
                                    {
                                        "id": "140"
                                    },
                                    {
                                        "id": "141"
                                    },
                                    {
                                        "id": "142"
                                    },
                                    {
                                        "id": "143"
                                    }
                                ]
                            },
                            {
                                "shapeIDCount": "12",
                                "shapeIDs": [
                                    {
                                        "id": "55"
                                    },
                                    {
                                        "id": "99"
                                    },
                                    {
                                        "id": "27"
                                    },
                                    {
                                        "id": "19"
                                    },
                                    {
                                        "id": "98"
                                    },
                                    {
                                        "id": "26"
                                    },
                                    {
                                        "id": "28"
                                    },
                                    {
                                        "id": "97"
                                    },
                                    {
                                        "id": "100"
                                    },
                                    {
                                        "id": "101"
                                    },
                                    {
                                        "id": "102"
                                    },
                                    {
                                        "id": "114"
                                    }
                                ]
                            }
                        ]
                            }
                        ]
                    },
                    {
                        "name": "Profile Feature(s)",
                        "color": "(0, 200, 100)",
                        "totalGroupFeatureCount": "1",
                        "featureCount": "1",
                        "features": [
                            {
                                "shapeIDCount": "70",
                                "shapeIDs": [
                                    {
                                        "id": "7"
                                    },
                                    {
                                        "id": "137"
                                    },
                                    {
                                        "id": "154"
                                    },
                                    {
                                        "id": "10"
                                    },
                                    {
                                        "id": "134"
                                    },
                                    {
                                        "id": "123"
                                    },
                                    {
                                        "id": "128"
                                    },
                                    {
                                        "id": "14"
                                    },
                                    {
                                        "id": "124"
                                    },
                                    {
                                        "id": "127"
                                    },
                                    {
                                        "id": "15"
                                    },
                                    {
                                        "id": "131"
                                    },
                                    {
                                        "id": "11"
                                    },
                                    {
                                        "id": "133"
                                    },
                                    {
                                        "id": "155"
                                    },
                                    {
                                        "id": "159"
                                    },
                                    {
                                        "id": "16"
                                    },
                                    {
                                        "id": "126"
                                    },
                                    {
                                        "id": "81"
                                    },
                                    {
                                        "id": "59"
                                    },
                                    {
                                        "id": "68"
                                    },
                                    {
                                        "id": "79"
                                    },
                                    {
                                        "id": "86"
                                    },
                                    {
                                        "id": "20"
                                    },
                                    {
                                        "id": "112"
                                    },
                                    {
                                        "id": "83"
                                    },
                                    {
                                        "id": "52"
                                    },
                                    {
                                        "id": "45"
                                    },
                                    {
                                        "id": "44"
                                    },
                                    {
                                        "id": "46"
                                    },
                                    {
                                        "id": "41"
                                    },
                                    {
                                        "id": "51"
                                    },
                                    {
                                        "id": "53"
                                    },
                                    {
                                        "id": "42"
                                    },
                                    {
                                        "id": "50"
                                    },
                                    {
                                        "id": "54"
                                    },
                                    {
                                        "id": "43"
                                    },
                                    {
                                        "id": "48"
                                    },
                                    {
                                        "id": "49"
                                    },
                                    {
                                        "id": "22"
                                    },
                                    {
                                        "id": "110"
                                    },
                                    {
                                        "id": "82"
                                    },
                                    {
                                        "id": "84"
                                    },
                                    {
                                        "id": "24"
                                    },
                                    {
                                        "id": "106"
                                    },
                                    {
                                        "id": "108"
                                    },
                                    {
                                        "id": "21"
                                    },
                                    {
                                        "id": "111"
                                    },
                                    {
                                        "id": "113"
                                    },
                                    {
                                        "id": "23"
                                    },
                                    {
                                        "id": "109"
                                    },
                                    {
                                        "id": "107"
                                    },
                                    {
                                        "id": "25"
                                    },
                                    {
                                        "id": "105"
                                    },
                                    {
                                        "id": "85"
                                    },
                                    {
                                        "id": "117"
                                    },
                                    {
                                        "id": "157"
                                    },
                                    {
                                        "id": "8"
                                    },
                                    {
                                        "id": "136"
                                    },
                                    {
                                        "id": "122"
                                    },
                                    {
                                        "id": "130"
                                    },
                                    {
                                        "id": "12"
                                    },
                                    {
                                        "id": "125"
                                    },
                                    {
                                        "id": "129"
                                    },
                                    {
                                        "id": "13"
                                    },
                                    {
                                        "id": "132"
                                    },
                                    {
                                        "id": "9"
                                    },
                                    {
                                        "id": "135"
                                    },
                                    {
                                        "id": "156"
                                    },
                                    {
                                        "id": "158"
                                    }
                                ]
                            }
                        ]
                    }
                ]
            }
        }
    ]
}