{
    "version": "1",
    "parts": [
        {
            "partId": "part-001",
            "partName": "CNC_Part",
            "geometricProperties": {
                "volume": "198677.46",
                "surfaceArea": "168874.82",
                "AABB": {
                    "dimensions": {
                        "x": "6.00",
                        "y": "354.00",
                        "z": "229.50"
                    },
                    "minCorner": {
                        "x": "-0.00",
                        "y": "-0.00",
                        "z": "-229.50"
                    },
                    "maxCorner": {
                        "x": "6.00",
                        "y": "354.00",
                        "z": "0.00"
                    }
                }
            },
            "process": "CNC Machining Milling",
            "featureRecognition": {
                "name": "Feature Recognition",
                "totalFeatureCount": "24",
                "featureGroups": [
                    {
                        "name": "Flat Face Milled Face(s)",
                        "color": "(115, 251, 253)",
                        "totalGroupFeatureCount": "2",
                        "featureCount": "2",
                        "features": [
                            {
                                "shapeIDCount": "1",
                                "shapeIDs": [
                                    {
                                        "id": "25"
                                    }
                                ]
                            },
                            {
                                "shapeIDCount": "1",
                                "shapeIDs": [
                                    {
                                        "id": "26"
                                    }
                                ]
                            }
                        ]
                    },
                    {
                        "name": "Through Hole(s)",
                        "color": "(240, 135, 132)",
                        "totalGroupFeatureCount": "6",
                        "subGroupCount": "1",
                        "subGroups": [
                            {
                                "parametersCount": "3",
                                "parameters": [
                                    {
                                        "name": "Radius",
                                        "units": "mm",
                                        "value": "1.100000"
                                    },
                                    {
                                        "name": "Depth",
                                        "units": "mm",
                                        "value": "2.000000"
                                    },
                                    {
                                        "name": "Axis",
                                        "units": "",
                                        "value": "(1.00, 0.00, 0.00)"
                                    }
                                ],
                                "featureCount": "6",
                        "features": [
                            {
                                "shapeIDCount": "1",
                                "shapeIDs": [
                                    {
                                        "id": "64"
                                    }
                                ]
                            },
                            {
                                "shapeIDCount": "1",
                                "shapeIDs": [
                                    {
                                        "id": "65"
                                    }
                                ]
                            },
                            {
                                "shapeIDCount": "1",
                                "shapeIDs": [
                                    {
                                        "id": "66"
                                    }
                                ]
                            },
                            {
                                "shapeIDCount": "1",
                                "shapeIDs": [
                                    {
                                        "id": "67"
                                    }
                                ]
                            },
                            {
                                "shapeIDCount": "1",
                                "shapeIDs": [
                                    {
                                        "id": "68"
                                    }
                                ]
                            },
                            {
                                "shapeIDCount": "1",
                                "shapeIDs": [
                                    {
                                        "id": "69"
                                    }
                                ]
                            }
                        ]
                            }
                        ]
                    },
                    {
                        "name": "Closed Pocket(s)",
                        "color": "(81, 20, 0)",
                        "totalGroupFeatureCount": "11",
                        "subGroupCount": "1",
                        "subGroups": [
                            {
                                "parametersCount": "4",
                                "parameters": [
                                    {
                                        "name": "Length",
                                        "units": "mm",
                                        "value": "350.000000"
                                    },
                                    {
                                        "name": "Width",
                                        "units": "mm",
                                        "value": "4.000000"
                                    },
                                    {
                                        "name": "Depth",
                                        "units": "mm",
                                        "value": "225.500000"
                                    },
                                    {
                                        "name": "Axis",
                                        "units": "",
                                        "value": "(0.00, 0.00, -1.00)"
                                    }
                                ],
                                "featureCount": "11",
                        "features": [
                            {
                                "shapeIDCount": "5",
                                "shapeIDs": [
                                    {
                                        "id": "63"
                                    },
                                    {
                                        "id": "1"
                                    },
                                    {
                                        "id": "2"
                                    },
                                    {
                                        "id": "3"
                                    },
                                    {
                                        "id": "4"
                                    }
                                ]
                            },
                            {
                                "shapeIDCount": "5",
                                "shapeIDs": [
                                    {
                                        "id": "7"
                                    },
                                    {
                                        "id": "2"
                                    },
                                    {
                                        "id": "36"
                                    },
                                    {
                                        "id": "45"
                                    },
                                    {
                                        "id": "46"
                                    }
                                ]
                            },
                            {
                                "shapeIDCount": "5",
                                "shapeIDs": [
                                    {
                                        "id": "8"
                                    },
                                    {
                                        "id": "48"
                                    },
                                    {
                                        "id": "2"
                                    },
                                    {
                                        "id": "37"
                                    },
                                    {
                                        "id": "47"
                                    }
                                ]
                            },
                            {
                                "shapeIDCount": "5",
                                "shapeIDs": [
                                    {
                                        "id": "12"
                                    },
                                    {
                                        "id": "4"
                                    },
                                    {
                                        "id": "39"
                                    },
                                    {
                                        "id": "55"
                                    },
                                    {
                                        "id": "56"
                                    }
                                ]
                            },
                            {
                                "shapeIDCount": "5",
                                "shapeIDs": [
                                    {
                                        "id": "13"
                                    },
                                    {
                                        "id": "4"
                                    },
                                    {
                                        "id": "40"
                                    },
                                    {
                                        "id": "57"
                                    },
                                    {
                                        "id": "58"
                                    }
                                ]
                            },
                            {
                                "shapeIDCount": "5",
                                "shapeIDs": [
                                    {
                                        "id": "15"
                                    },
                                    {
                                        "id": "1"
                                    },
                                    {
                                        "id": "41"
                                    },
                                    {
                                        "id": "61"
                                    },
                                    {
                                        "id": "62"
                                    }
                                ]
                            },
                            {
                                "shapeIDCount": "5",
                                "shapeIDs": [
                                    {
                                        "id": "10"
                                    },
                                    {
                                        "id": "3"
                                    },
                                    {
                                        "id": "51"
                                    },
                                    {
                                        "id": "38"
                                    },
                                    {
                                        "id": "52"
                                    }
                                ]
                            },
                            {
                                "shapeIDCount": "5",
                                "shapeIDs": [
                                    {
                                        "id": "6"
                                    },
                                    {
                                        "id": "1"
                                    },
                                    {
                                        "id": "2"
                                    },
                                    {
                                        "id": "43"
                                    },
                                    {
                                        "id": "44"
                                    }
                                ]
                            },
                            {
                                "shapeIDCount": "5",
                                "shapeIDs": [
                                    {
                                        "id": "9"
                                    },
                                    {
                                        "id": "49"
                                    },
                                    {
                                        "id": "2"
                                    },
                                    {
                                        "id": "50"
                                    },
                                    {
                                        "id": "3"
                                    }
                                ]
                            },
                            {
                                "shapeIDCount": "5",
                                "shapeIDs": [
                                    {
                                        "id": "11"
                                    },
                                    {
                                        "id": "3"
                                    },
                                    {
                                        "id": "4"
                                    },
                                    {
                                        "id": "53"
                                    },
                                    {
                                        "id": "54"
                                    }
                                ]
                            },
                            {
                                "shapeIDCount": "5",
                                "shapeIDs": [
                                    {
                                        "id": "14"
                                    },
                                    {
                                        "id": "1"
                                    },
                                    {
                                        "id": "4"
                                    },
                                    {
                                        "id": "60"
                                    },
                                    {
                                        "id": "59"
                                    }
                                ]
                            }
                        ]
                            }
                        ]
                    },
                    {
                        "name": "Open Pocket(s)",
                        "color": "(120, 60, 30)",
                        "totalGroupFeatureCount": "2",
                        "subGroupCount": "1",
                        "subGroups": [
                            {
                                "parametersCount": "4",
                                "parameters": [
                                    {
                                        "name": "Length",
                                        "units": "mm",
                                        "value": "107.000000"
                                    },
                                    {
                                        "name": "Width",
                                        "units": "mm",
                                        "value": "1.300000"
                                    },
                                    {
                                        "name": "Depth",
                                        "units": "mm",
                                        "value": "89.500000"
                                    },
                                    {
                                        "name": "Axis",
                                        "units": "",
                                        "value": "(0.00, 0.00, -1.00)"
                                    }
                                ],
                                "featureCount": "2",
                        "features": [
                            {
                                "shapeIDCount": "6",
                                "shapeIDs": [
                                    {
                                        "id": "5"
                                    },
                                    {
                                        "id": "30"
                                    },
                                    {
                                        "id": "31"
                                    },
                                    {
                                        "id": "32"
                                    },
                                    {
                                        "id": "33"
                                    },
                                    {
                                        "id": "34"
                                    }
                                ]
                            },
                            {
                                "shapeIDCount": "6",
                                "shapeIDs": [
                                    {
                                        "id": "16"
                                    },
                                    {
                                        "id": "27"
                                    },
                                    {
                                        "id": "35"
                                    },
                                    {
                                        "id": "28"
                                    },
                                    {
                                        "id": "29"
                                    },
                                    {
                                        "id": "42"
                                    }
                                ]
                            }
                        ]
                            }
                        ]
                    },
                    {
                        "name": "Through Pocket(s)",
                        "color": "(160, 100, 60)",
                        "totalGroupFeatureCount": "1",
                        "subGroupCount": "1",
                        "subGroups": [
                            {
                                "parametersCount": "3",
                                "parameters": [
                                    {
                                        "name": "Length",
                                        "units": "mm",
                                        "value": "81.000000"
                                    },
                                    {
                                        "name": "Width",
                                        "units": "mm",
                                        "value": "3.300000"
                                    },
                                    {
                                        "name": "Axis",
                                        "units": "",
                                        "value": "(0.00, 0.00, -1.00)"
                                    }
                                ],
                                "featureCount": "1",
                        "features": [
                            {
                                "shapeIDCount": "4",
                                "shapeIDs": [
                                    {
                                        "id": "17"
                                    },
                                    {
                                        "id": "18"
                                    },
                                    {
                                        "id": "24"
                                    },
                                    {
                                        "id": "19"
                                    }
                                ]
                            }
                        ]
                            }
                        ]
                    },
                    {
                        "name": "Profile Feature(s)",
                        "color": "(0, 200, 100)",
                        "totalGroupFeatureCount": "1",
                        "featureCount": "1",
                        "features": [
                            {
                                "shapeIDCount": "8",
                                "shapeIDs": [
                                    {
                                        "id": "20"
                                    },
                                    {
                                        "id": "70"
                                    },
                                    {
                                        "id": "23"
                                    },
                                    {
                                        "id": "75"
                                    },
                                    {
                                        "id": "22"
                                    },
                                    {
                                        "id": "81"
                                    },
                                    {
                                        "id": "21"
                                    },
                                    {
                                        "id": "72"
                                    }
                                ]
                            }
                        ]
                    },
                    {
                        "name": "Fillet(s)",
                        "color": "(0, 191, 255)",
                        "totalGroupFeatureCount": "1",
                        "subGroupCount": "1",
                        "subGroups": [
                            {
                                "parametersCount": "2",
                                "parameters": [
                                    {
                                        "name": "Radius",
                                        "units": "mm",
                                        "value": "1.000000"
                                    },
                                    {
                                        "name": "IsConvex",
                                        "units": "",
                                        "value": "true"
                                    }
                                ],
                                "featureCount": "1",
                        "features": [
                            {
                                "shapeIDCount": "8",
                                "shapeIDs": [
                                    {
                                        "id": "71"
                                    },
                                    {
                                        "id": "73"
                                    },
                                    {
                                        "id": "76"
                                    },
                                    {
                                        "id": "74"
                                    },
                                    {
                                        "id": "77"
                                    },
                                    {
                                        "id": "78"
                                    },
                                    {
                                        "id": "79"
                                    },
                                    {
                                        "id": "80"
                                    }
                                ]
                            }
                        ]
                            }
                        ]
                    }
                ]
            }
        }
    ]
}